{
    "game": [
        {
            "Home_team": "Hawks",
            "Away_team": "Bulls",
            "GameId": "0022400413",
            "HomeTeamScore": 141,
            "VisitorTeamScore": 133,
            "GameDate": "2024-12-26T19:30:00",
            "HomeTeamId": 1610612737,
            "AwayTeamId": 1610612741,
            "Home_team_abbr": "ATL",
            "Away_team_abbr": "CHI",
            "L2M_Comments": null,
            "GameDateOut": "December 26, 2024"
        }
    ],
    "stats": [
        {
            "stats_name": "Calls",
            "home": 0,
            "away": 0
        },
        {
            "stats_name": "Errors in Favor",
            "home": 0,
            "away": 0
        },
        {
            "stats_name": "Possessions in Favor",
            "home": 0,
            "away": 0
        }
    ],
    "l2m": [
        {
            "PeriodName": "Q4",
            "PCTime": "01:51.0",
            "ImposibleIndicator": 0,
            "Comment": "Hunter (ATL) cleanly blocks the jump shot attempt by Williams (CHI) and any ensuing contact is incidental.",
            "CallRatingName": "CNC",
            "CallType": "Foul: Shooting",
            "CP": "De'Andre Hunter",
            "DP": "Patrick Williams",
            "Difficulty": "Observable",
            "VideolLink": "2150",
            "Qualifier": null,
            "posID": 1542,
            "posStart": "02:00.6",
            "posEnd": "01:47.3",
            "posTeamId": 1610612741,
            "teamIdInFavor": null,
            "errorInFavor": "",
            "imgChart": 26.530613
        },
        {
            "PeriodName": "Q4",
            "PCTime": "01:49.7",
            "ImposibleIndicator": 0,
            "Comment": "Hunter (ATL) is the last play to touch the ball before it goes out of bounds.",
            "CallRatingName": "CC",
            "CallType": "Stoppage: Out-of-Bounds",
            "CP": "De'Andre Hunter",
            "DP": "Patrick Williams",
            "Difficulty": "Observable",
            "VideolLink": "2151",
            "Qualifier": null,
            "posID": 1542,
            "posStart": "02:00.6",
            "posEnd": "01:47.3",
            "posTeamId": 1610612741,
            "teamIdInFavor": null,
            "errorInFavor": "",
            "imgChart": 26.530613
        },
        {
            "PeriodName": "Q4",
            "PCTime": "01:36.7",
            "ImposibleIndicator": 0,
            "Comment": "Williams (CHI) contests Capela&apos;s (ATL) dunk attempt and the contact with Capela&apos;s head is marginal.",
            "CallRatingName": "CNC",
            "CallType": "Foul: Shooting",
            "CP": "Patrick Williams",
            "DP": "Clint Capela",
            "Difficulty": "Observable",
            "VideolLink": "2152",
            "Qualifier": null,
            "posID": 1543,
            "posStart": "01:47.3",
            "posEnd": "01:36.5",
            "posTeamId": 1610612737,
            "teamIdInFavor": null,
            "errorInFavor": "",
            "imgChart": 20.408163
        },
        {
            "PeriodName": "Q4",
            "PCTime": "01:25.2",
            "ImposibleIndicator": 0,
            "Comment": "LaVine (CHI) briefly places an arm at Johnson&apos;s (ATL) side before immediately correcting and legally contesting the shot attempt.",
            "CallRatingName": "CNC",
            "CallType": "Foul: Shooting",
            "CP": "Zach LaVine",
            "DP": "Jalen Johnson",
            "Difficulty": "Observable",
            "VideolLink": "2153",
            "Qualifier": null,
            "posID": 1545,
            "posStart": "01:29.1",
            "posEnd": "01:23.6",
            "posTeamId": 1610612737,
            "teamIdInFavor": null,
            "errorInFavor": "",
            "imgChart": 10.204082
        },
        {
            "PeriodName": "Q4",
            "PCTime": "00:59.3",
            "ImposibleIndicator": 0,
            "Comment": "Carter (CHI) moves laterally into Young&apos;s (ATL) path and initiates body contact that affects his SQBR.",
            "CallRatingName": "CC",
            "CallType": "Foul: Personal",
            "CP": "Jevon Carter",
            "DP": "Trae Young",
            "Difficulty": "Observable",
            "VideolLink": "2154",
            "Qualifier": null,
            "posID": 1547,
            "posStart": "01:11.6",
            "posEnd": "00:59.3",
            "posTeamId": 1610612737,
            "teamIdInFavor": null,
            "errorInFavor": "",
            "imgChart": 24.489796
        },
        {
            "PeriodName": "Q4",
            "PCTime": "00:29.6",
            "ImposibleIndicator": 0,
            "Comment": "Vucevic (CHI) initiates contact with Hunter&apos;s (ATL) arm, which affects his play at the basket.",
            "CallRatingName": "CC",
            "CallType": "Foul: Shooting",
            "CP": "Nikola Vucevic",
            "DP": "De'Andre Hunter",
            "Difficulty": "Observable",
            "VideolLink": "2155",
            "Qualifier": null,
            "posID": 1549,
            "posStart": "00:47.5",
            "posEnd": "00:29.6",
            "posTeamId": 1610612737,
            "teamIdInFavor": null,
            "errorInFavor": "",
            "imgChart": 34.69388
        },
        {
            "PeriodName": "Q4",
            "PCTime": "00:29.6",
            "ImposibleIndicator": 0,
            "Comment": "Vucevic (CHI) is assessed an unsportsmanlike technical foul.",
            "CallRatingName": "CC",
            "CallType": "Foul: Technical",
            "CP": "Nikola Vucevic",
            "DP": "Hawks",
            "Difficulty": "Observable",
            "VideolLink": "2155",
            "Qualifier": null,
            "posID": 1549,
            "posStart": "00:47.5",
            "posEnd": "00:29.6",
            "posTeamId": 1610612737,
            "teamIdInFavor": null,
            "errorInFavor": "",
            "imgChart": 34.69388
        },
        {
            "PeriodName": "Q4",
            "PCTime": "00:19.9",
            "ImposibleIndicator": 0,
            "Comment": "Daniels (ATL) maintains a legal guarding position during LaVine&apos;s (CHI) drive to the basket and shot attempt.",
            "CallRatingName": "CNC",
            "CallType": "Foul: Shooting",
            "CP": "Dyson Daniels",
            "DP": "Zach LaVine",
            "Difficulty": "Observable",
            "VideolLink": "2156",
            "Qualifier": null,
            "posID": 1550,
            "posStart": "00:29.6",
            "posEnd": "00:19.2",
            "posTeamId": 1610612741,
            "teamIdInFavor": null,
            "errorInFavor": "",
            "imgChart": 20.408163
        },
        {
            "PeriodName": "Q4",
            "PCTime": "00:17.5",
            "ImposibleIndicator": 0,
            "Comment": "Carter (CHI) commits a take foul on Young (ATL). The transition take foul rule does not apply to the last two minutes of either the fourth quarter or overtime.",
            "CallRatingName": "CC",
            "CallType": "Foul: Personal",
            "CP": "Jevon Carter",
            "DP": "Trae Young",
            "Difficulty": "Observable",
            "VideolLink": "2157",
            "Qualifier": null,
            "posID": 1551,
            "posStart": "00:19.2",
            "posEnd": "00:17.5",
            "posTeamId": 1610612737,
            "teamIdInFavor": null,
            "errorInFavor": "",
            "imgChart": 2.0408163
        },
        {
            "PeriodName": "Q4",
            "PCTime": "00:14.6",
            "ImposibleIndicator": 0,
            "Comment": "Hunter (ATL) contests the jump shot attempt and avoids making contact with Williams (CHI).",
            "CallRatingName": "CNC",
            "CallType": "Foul: Shooting",
            "CP": "De'Andre Hunter",
            "DP": "Patrick Williams",
            "Difficulty": "Observable",
            "VideolLink": "2158",
            "Qualifier": null,
            "posID": 1552,
            "posStart": "00:17.5",
            "posEnd": "00:11.7",
            "posTeamId": 1610612741,
            "teamIdInFavor": null,
            "errorInFavor": "",
            "imgChart": 10.204082
        }
    ]
}