{
    "game": [
        {
            "Home_team": "Hornets",
            "Away_team": "Nuggets",
            "GameId": "0022400688",
            "HomeTeamScore": 104,
            "VisitorTeamScore": 107,
            "GameDate": "2025-02-01T19:00:00",
            "HomeTeamId": 1610612766,
            "AwayTeamId": 1610612743,
            "Home_team_abbr": "CHA",
            "Away_team_abbr": "DEN",
            "L2M_Comments": null,
            "GameDateOut": "February 01, 2025"
        }
    ],
    "stats": [
        {
            "stats_name": "Calls",
            "home": 2,
            "away": 0
        },
        {
            "stats_name": "Errors in Favor",
            "home": 1,
            "away": 0
        },
        {
            "stats_name": "Possessions in Favor",
            "home": 0,
            "away": 0
        }
    ],
    "l2m": [
        {
            "PeriodName": "Q4",
            "PCTime": "01:57.0",
            "ImposibleIndicator": 0,
            "Comment": "Williams (CHA) firms up over his right foot in Gordon&apos;s (DEN) path when marginal contact occurs to his side as the screen is set.",
            "CallRatingName": "CNC",
            "CallType": "Foul: Offensive",
            "CP": "Mark Williams",
            "DP": "Aaron Gordon",
            "Difficulty": "Observable",
            "VideolLink": "2128",
            "Qualifier": null,
            "posID": 1537,
            "posStart": "02:01.0",
            "posEnd": "01:25.1",
            "posTeamId": 1610612766,
            "teamIdInFavor": null,
            "errorInFavor": "",
            "imgChart": 71.42857
        },
        {
            "PeriodName": "Q4",
            "PCTime": "01:49.3",
            "ImposibleIndicator": 0,
            "Comment": "After the pick, Green (CHA) attempts to roll toward the basket when Gordon (DEN) wraps his arms around Green, which affects his FOM off-ball.",
            "CallRatingName": "CC",
            "CallType": "Foul: Personal",
            "CP": "Aaron Gordon",
            "DP": "Josh Green",
            "Difficulty": "Observable",
            "VideolLink": "2129",
            "Qualifier": null,
            "posID": 1537,
            "posStart": "02:01.0",
            "posEnd": "01:25.1",
            "posTeamId": 1610612766,
            "teamIdInFavor": null,
            "errorInFavor": "",
            "imgChart": 71.42857
        },
        {
            "PeriodName": "Q4",
            "PCTime": "01:40.8",
            "ImposibleIndicator": 0,
            "Comment": "Murray (DEN) moves alongside Bridges&apos; (CHA) path and marginal body contact occurs during the driving shot attempt.",
            "CallRatingName": "CNC",
            "CallType": "Foul: Shooting",
            "CP": "Jamal Murray",
            "DP": "Miles Bridges",
            "Difficulty": "Observable",
            "VideolLink": "2130",
            "Qualifier": null,
            "posID": 1537,
            "posStart": "02:01.0",
            "posEnd": "01:25.1",
            "posTeamId": 1610612766,
            "teamIdInFavor": null,
            "errorInFavor": "",
            "imgChart": 71.42857
        },
        {
            "PeriodName": "Q4",
            "PCTime": "01:26.6",
            "ImposibleIndicator": 0,
            "Comment": "Murray (DEN) aligns alongside Bridges&apos; (CHA) path when marginal contact occurs as he slides his hand off Bridges during the driving shot attempt.",
            "CallRatingName": "CNC",
            "CallType": "Foul: Shooting",
            "CP": "Jamal Murray",
            "DP": "Miles Bridges",
            "Difficulty": "Observable",
            "VideolLink": "2131",
            "Qualifier": null,
            "posID": 1537,
            "posStart": "02:01.0",
            "posEnd": "01:25.1",
            "posTeamId": 1610612766,
            "teamIdInFavor": null,
            "errorInFavor": "",
            "imgChart": 71.42857
        },
        {
            "PeriodName": "Q4",
            "PCTime": "00:53.5",
            "ImposibleIndicator": 0,
            "Comment": "Bridges (CHA) gathers the ball on his right foot and takes two steps before shooting.",
            "CallRatingName": "CNC",
            "CallType": "Turnover: Traveling",
            "CP": "Miles Bridges",
            "DP": "Nuggets",
            "Difficulty": "Observable",
            "VideolLink": "2132",
            "Qualifier": null,
            "posID": 1539,
            "posStart": "01:11.9",
            "posEnd": "00:51.5",
            "posTeamId": 1610612766,
            "teamIdInFavor": null,
            "errorInFavor": "",
            "imgChart": 40.816326
        },
        {
            "PeriodName": "Q4",
            "PCTime": "00:41.9",
            "ImposibleIndicator": 0,
            "Comment": "Williams (CHA) jumps forward as he contests and initiates illegal body contact with Jokic (DEN) during his upward shooting motion.",
            "CallRatingName": "CC",
            "CallType": "Foul: Shooting",
            "CP": "Mark Williams",
            "DP": "Nikola Jokic",
            "Difficulty": "Observable",
            "VideolLink": "2133",
            "Qualifier": null,
            "posID": 1540,
            "posStart": "00:51.5",
            "posEnd": "00:41.9",
            "posTeamId": 1610612743,
            "teamIdInFavor": null,
            "errorInFavor": "",
            "imgChart": 18.367348
        },
        {
            "PeriodName": "Q4",
            "PCTime": "00:24.0",
            "ImposibleIndicator": 0,
            "Comment": "Jokic (DEN) is in the paint for less than three seconds when the shot is imminent.",
            "CallRatingName": "CNC",
            "CallType": "Foul: Defense 3 Second",
            "CP": "Nikola Jokic",
            "DP": "Hornets",
            "Difficulty": "Observable",
            "VideolLink": "2134",
            "Qualifier": null,
            "posID": 1541,
            "posStart": "00:41.9",
            "posEnd": "00:20.9",
            "posTeamId": 1610612766,
            "teamIdInFavor": null,
            "errorInFavor": "",
            "imgChart": 42.857143
        },
        {
            "PeriodName": "Q4",
            "PCTime": "00:18.6",
            "ImposibleIndicator": 0,
            "Comment": "Replay review of the foul called on Green (CHA) pursuant to a coach&apos;s challenge was deemed unsuccessful. Although Green (CHA) initially makes contact with the ball, he then pulls Jokic&apos;s (DEN) hand off it while making further contact with Jokic&apos;s right arm.",
            "CallRatingName": "CC",
            "CallType": "Foul: Personal",
            "CP": "Josh Green",
            "DP": "Nikola Jokic",
            "Difficulty": "Observable",
            "VideolLink": "2135",
            "Qualifier": null,
            "posID": 1542,
            "posStart": "00:20.9",
            "posEnd": "00:19.6",
            "posTeamId": 1610612743,
            "teamIdInFavor": null,
            "errorInFavor": "",
            "imgChart": 2.0408163
        },
        {
            "PeriodName": "Q4",
            "PCTime": "00:14.4",
            "ImposibleIndicator": 0,
            "Comment": "Gordon (DEN) maintains a legal guarding position as he moves alongside Bridges&apos; (CHA) path when incidental body contact occurs during the driving shot attempt.",
            "CallRatingName": "CNC",
            "CallType": "Foul: Shooting",
            "CP": "Aaron Gordon",
            "DP": "Miles Bridges",
            "Difficulty": "Observable",
            "VideolLink": "2136",
            "Qualifier": null,
            "posID": 1543,
            "posStart": "00:19.6",
            "posEnd": "00:13.1",
            "posTeamId": 1610612766,
            "teamIdInFavor": null,
            "errorInFavor": "",
            "imgChart": 12.244898
        },
        {
            "PeriodName": "Q4",
            "PCTime": "00:08.9",
            "ImposibleIndicator": 0,
            "Comment": "Green (CHA) grasps and immediately releases Murray&apos;s (DEN) jersey causing marginal contact to occur after Murray gathers.",
            "CallRatingName": "CNC",
            "CallType": "Foul: Shooting",
            "CP": "Josh Green",
            "DP": "Jamal Murray",
            "Difficulty": "Observable",
            "VideolLink": "2137",
            "Qualifier": null,
            "posID": 1544,
            "posStart": "00:13.1",
            "posEnd": "00:08.0",
            "posTeamId": 1610612743,
            "teamIdInFavor": null,
            "errorInFavor": "",
            "imgChart": 10.204082
        },
        {
            "PeriodName": "Q4",
            "PCTime": "00:06.9",
            "ImposibleIndicator": 0,
            "Comment": "Murray (DEN) avoids making any arm contact with Smith Jr. (CHA) as he loses control of the ball during his upwards shooting motion.",
            "CallRatingName": "CNC",
            "CallType": "Foul: Shooting",
            "CP": "Jamal Murray",
            "DP": "Nick Smith Jr.",
            "Difficulty": "Observable",
            "VideolLink": "2138",
            "Qualifier": null,
            "posID": 1545,
            "posStart": "00:08.0",
            "posEnd": "00:00.0",
            "posTeamId": 1610612766,
            "teamIdInFavor": null,
            "errorInFavor": "",
            "imgChart": 16.32653
        },
        {
            "PeriodName": "Q4",
            "PCTime": "00:05.5",
            "ImposibleIndicator": 0,
            "Comment": "Smith Jr. (CHA) takes a dribble and fumbles the ball naturally during his upward shooting motion. He is allowed to be the first to touch as long as he does not dribble again, which he does here.",
            "CallRatingName": "INC",
            "CallType": "Turnover: Double Dribble",
            "CP": "Nick Smith Jr.",
            "DP": "Nuggets",
            "Difficulty": "Observable",
            "VideolLink": "2139",
            "Qualifier": null,
            "posID": 1545,
            "posStart": "00:08.0",
            "posEnd": "00:00.0",
            "posTeamId": 1610612766,
            "teamIdInFavor": null,
            "errorInFavor": "",
            "imgChart": 16.32653
        },
        {
            "PeriodName": "Q4",
            "PCTime": "00:03.5",
            "ImposibleIndicator": 0,
            "Comment": "Murray (DEN) contests the jump shot attempt and avoids making contact with Smith Jr.&apos;s (CHA) arm.",
            "CallRatingName": "CNC",
            "CallType": "Foul: Shooting",
            "CP": "Jamal Murray",
            "DP": "Nick Smith Jr.",
            "Difficulty": "Observable",
            "VideolLink": "2140",
            "Qualifier": null,
            "posID": 1545,
            "posStart": "00:08.0",
            "posEnd": "00:00.0",
            "posTeamId": 1610612766,
            "teamIdInFavor": null,
            "errorInFavor": "",
            "imgChart": 16.32653
        },
        {
            "PeriodName": "Q4",
            "PCTime": "00:00.0",
            "ImposibleIndicator": 0,
            "Comment": "Williams (CHA) does not release the ball prior to the expiration of the game clock.",
            "CallRatingName": "CC",
            "CallType": "Instant Replay: Support Ruling",
            "CP": "Hornets",
            "DP": "Nuggets",
            "Difficulty": "",
            "VideolLink": "2141",
            "Qualifier": null,
            "posID": 1545,
            "posStart": "00:08.0",
            "posEnd": "00:00.0",
            "posTeamId": 1610612766,
            "teamIdInFavor": null,
            "errorInFavor": "",
            "imgChart": 16.32653
        }
    ]
}