{
    "game": [
        {
            "Home_team": "Lakers",
            "Away_team": "Hornets",
            "GameId": "0022400524",
            "HomeTeamScore": 97,
            "VisitorTeamScore": 100,
            "GameDate": "2025-02-19T22:00:00",
            "HomeTeamId": 1610612747,
            "AwayTeamId": 1610612766,
            "Home_team_abbr": "LAL",
            "Away_team_abbr": "CHA",
            "L2M_Comments": null,
            "GameDateOut": "February 19, 2025"
        }
    ],
    "stats": [
        {
            "stats_name": "Calls",
            "home": 1,
            "away": 1
        },
        {
            "stats_name": "Errors in Favor",
            "home": 0,
            "away": 0
        },
        {
            "stats_name": "Possessions in Favor",
            "home": 0,
            "away": 0
        }
    ],
    "l2m": [
        {
            "PeriodName": "Q4",
            "PCTime": "01:54.9",
            "ImposibleIndicator": 0,
            "Comment": "Doncic (LAL) legally contests Bridges&apos; (CHA) jump shot attempt.",
            "CallRatingName": "CNC",
            "CallType": "Foul: Shooting",
            "CP": "Luka Doncic",
            "DP": "Miles Bridges",
            "Difficulty": "Observable",
            "VideolLink": "2117",
            "Qualifier": null,
            "posID": 1539,
            "posStart": "02:13.7",
            "posEnd": "01:53.0",
            "posTeamId": 1610612766,
            "teamIdInFavor": null,
            "errorInFavor": "",
            "imgChart": 40.816326
        },
        {
            "PeriodName": "Q4",
            "PCTime": "01:48.5",
            "ImposibleIndicator": 0,
            "Comment": "Hayes (LAL) momentarily places his hands on Bridges&apos; (CHA) body as he releases away to roll to the basket.",
            "CallRatingName": "CNC",
            "CallType": "Foul: Offensive",
            "CP": "Jaxson Hayes",
            "DP": "Miles Bridges",
            "Difficulty": "Observable",
            "VideolLink": "2118",
            "Qualifier": null,
            "posID": 1540,
            "posStart": "01:53.0",
            "posEnd": "01:46.0",
            "posTeamId": 1610612747,
            "teamIdInFavor": null,
            "errorInFavor": "",
            "imgChart": 14.285714
        },
        {
            "PeriodName": "Q4",
            "PCTime": "01:26",
            "ImposibleIndicator": 0,
            "Comment": "Bridges (CHA) loses control of the ball on his own as he attempts to dribble between Hachimura (LAL) and Doncic (LAL). The ensuing contact with James (LAL) as Bridges dives to the floor to secure the loose ball is incidental.",
            "CallRatingName": "CNC",
            "CallType": "Foul: Personal",
            "CP": "Rui Hachimura",
            "DP": "Miles Bridges",
            "Difficulty": "Observable",
            "VideolLink": "2119",
            "Qualifier": null,
            "posID": 1541,
            "posStart": "01:46.0",
            "posEnd": "01:22.0",
            "posTeamId": 1610612766,
            "teamIdInFavor": null,
            "errorInFavor": "",
            "imgChart": 48.97959
        },
        {
            "PeriodName": "Q4",
            "PCTime": "01:21.4",
            "ImposibleIndicator": 0,
            "Comment": "The Hornets still have possession of the ball when the shot clock expires.",
            "CallRatingName": "CC",
            "CallType": "Turnover: 24 Second Violation",
            "CP": "Hornets",
            "DP": "Lakers",
            "Difficulty": "Observable",
            "VideolLink": "2120",
            "Qualifier": null,
            "posID": 1541,
            "posStart": "01:46.0",
            "posEnd": "01:22.0",
            "posTeamId": 1610612766,
            "teamIdInFavor": null,
            "errorInFavor": "",
            "imgChart": 48.97959
        },
        {
            "PeriodName": "Q4",
            "PCTime": "01:06.5",
            "ImposibleIndicator": 0,
            "Comment": "Green&apos;s (CHA) hand slides off the ball and the ensuing contact with Doncic&apos;s (LAL) wrist is marginal.",
            "CallRatingName": "CNC",
            "CallType": "Foul: Loose Ball",
            "CP": "Josh Green",
            "DP": "Luka Doncic",
            "Difficulty": "Observable",
            "VideolLink": "2121",
            "Qualifier": null,
            "posID": 1542,
            "posStart": "01:22.0",
            "posEnd": "01:03.9",
            "posTeamId": 1610612747,
            "teamIdInFavor": null,
            "errorInFavor": "",
            "imgChart": 36.734695
        },
        {
            "PeriodName": "Q4",
            "PCTime": "01:04.8",
            "ImposibleIndicator": 0,
            "Comment": "Green&apos;s (CHA) arm is not in a vertical position during Doncic&apos;s (LAL) shot attempt, but the contact is marginal.",
            "CallRatingName": "CNC",
            "CallType": "Foul: Shooting",
            "CP": "Josh Green",
            "DP": "Luka Doncic",
            "Difficulty": "Observable",
            "VideolLink": "2122",
            "Qualifier": null,
            "posID": 1542,
            "posStart": "01:22.0",
            "posEnd": "01:03.9",
            "posTeamId": 1610612747,
            "teamIdInFavor": null,
            "errorInFavor": "",
            "imgChart": 36.734695
        },
        {
            "PeriodName": "Q4",
            "PCTime": "00:37.4",
            "ImposibleIndicator": 0,
            "Comment": "Bridges (CHA) initiates contact with Hachimura&apos;s (LAL) arm during his upward shooting motion, which affects his play at the basket.",
            "CallRatingName": "CC",
            "CallType": "Foul: Shooting",
            "CP": "Miles Bridges",
            "DP": "Rui Hachimura",
            "Difficulty": "Observable",
            "VideolLink": "2123",
            "Qualifier": null,
            "posID": 1544,
            "posStart": "00:47.5",
            "posEnd": "00:37.4",
            "posTeamId": 1610612747,
            "teamIdInFavor": null,
            "errorInFavor": "",
            "imgChart": 20.408163
        },
        {
            "PeriodName": "Q4",
            "PCTime": "00:15.1",
            "ImposibleIndicator": 0,
            "Comment": "Vanderbilt (LAL) legally contests the driving shot attempt by Ball (CHA).",
            "CallRatingName": "CNC",
            "CallType": "Foul: Shooting",
            "CP": "Jarred Vanderbilt",
            "DP": "LaMelo Ball",
            "Difficulty": "Observable",
            "VideolLink": "2124",
            "Qualifier": null,
            "posID": 1545,
            "posStart": "00:37.4",
            "posEnd": "00:14.2",
            "posTeamId": 1610612766,
            "teamIdInFavor": null,
            "errorInFavor": "",
            "imgChart": 46.938774
        },
        {
            "PeriodName": "Q4",
            "PCTime": "00:14.2",
            "ImposibleIndicator": 0,
            "Comment": "Vincent (LAL) establishes himself in Smith Jr.&apos;s (CHA) path and absorbs the marginal contact as both players come together during the screen. ",
            "CallRatingName": "CNC",
            "CallType": "Foul: Offensive",
            "CP": "Gabe Vincent",
            "DP": "Nick Smith Jr.",
            "Difficulty": "Observable",
            "VideolLink": "2125",
            "Qualifier": null,
            "posID": 1546,
            "posStart": "00:14.2",
            "posEnd": "00:06.8",
            "posTeamId": 1610612747,
            "teamIdInFavor": null,
            "errorInFavor": "",
            "imgChart": 14.285714
        },
        {
            "PeriodName": "Q4",
            "PCTime": "00:08.4",
            "ImposibleIndicator": 0,
            "Comment": "Bridges (CHA) legally contests James&apos; (LAL) jump shot attempt.",
            "CallRatingName": "CNC",
            "CallType": "Foul: Shooting",
            "CP": "Miles Bridges",
            "DP": "LeBron James",
            "Difficulty": "Observable",
            "VideolLink": "2126",
            "Qualifier": null,
            "posID": 1546,
            "posStart": "00:14.2",
            "posEnd": "00:06.8",
            "posTeamId": 1610612747,
            "teamIdInFavor": null,
            "errorInFavor": "",
            "imgChart": 14.285714
        },
        {
            "PeriodName": "Q4",
            "PCTime": "00:06.3",
            "ImposibleIndicator": 0,
            "Comment": "Vincent (LAL) commits a take foul on Ball (CHA).",
            "CallRatingName": "CC",
            "CallType": "Foul: Personal",
            "CP": "Gabe Vincent",
            "DP": "LaMelo Ball",
            "Difficulty": "Observable",
            "VideolLink": "2127",
            "Qualifier": null,
            "posID": 1547,
            "posStart": "00:06.8",
            "posEnd": "00:06.3",
            "posTeamId": 1610612766,
            "teamIdInFavor": null,
            "errorInFavor": "",
            "imgChart": 1.0
        },
        {
            "PeriodName": "Q4",
            "PCTime": "00:06.3",
            "ImposibleIndicator": 0,
            "Comment": "Salaun (CHA) and Finney-Smith (LAL) briefly engage with each other during the throw-in.",
            "CallRatingName": "CNC",
            "CallType": "Foul: Personal",
            "CP": "Tidjane Salaun",
            "DP": "Dorian Finney-Smith",
            "Difficulty": "Observable",
            "VideolLink": "2128",
            "Qualifier": null,
            "posID": 1548,
            "posStart": "00:06.3",
            "posEnd": "00:00.0",
            "posTeamId": 1610612747,
            "teamIdInFavor": null,
            "errorInFavor": "",
            "imgChart": 12.244898
        },
        {
            "PeriodName": "Q4",
            "PCTime": "00:04.9",
            "ImposibleIndicator": 0,
            "Comment": "Salaun (CHA) legally contests James&apos; (LAL) jump shot attempt.",
            "CallRatingName": "CNC",
            "CallType": "Foul: Shooting",
            "CP": "Tidjane Salaun",
            "DP": "LeBron James",
            "Difficulty": "Observable",
            "VideolLink": "2129",
            "Qualifier": null,
            "posID": 1548,
            "posStart": "00:06.3",
            "posEnd": "00:00.0",
            "posTeamId": 1610612747,
            "teamIdInFavor": null,
            "errorInFavor": "",
            "imgChart": 12.244898
        },
        {
            "PeriodName": "Q4",
            "PCTime": "00:00.9",
            "ImposibleIndicator": 0,
            "Comment": "Bridges (CHA) legally contests James&apos; (LAL) jump shot attempt.",
            "CallRatingName": "CNC",
            "CallType": "Foul: Shooting",
            "CP": "Miles Bridges",
            "DP": "LeBron James",
            "Difficulty": "Observable",
            "VideolLink": "2130",
            "Qualifier": null,
            "posID": 1548,
            "posStart": "00:06.3",
            "posEnd": "00:00.0",
            "posTeamId": 1610612747,
            "teamIdInFavor": null,
            "errorInFavor": "",
            "imgChart": 12.244898
        }
    ]
}