{
    "game": [
        {
            "Home_team": "Kings",
            "Away_team": "Jazz",
            "GameId": "0022400233",
            "HomeTeamScore": 121,
            "VisitorTeamScore": 117,
            "GameDate": "2024-11-16T22:00:00",
            "HomeTeamId": 1610612758,
            "AwayTeamId": 1610612762,
            "Home_team_abbr": "SAC",
            "Away_team_abbr": "UTA",
            "L2M_Comments": null,
            "GameDateOut": "November 16, 2024"
        }
    ],
    "stats": [
        {
            "stats_name": "Calls",
            "home": 2,
            "away": 0
        },
        {
            "stats_name": "Errors in Favor",
            "home": 2,
            "away": 0
        },
        {
            "stats_name": "Possessions in Favor",
            "home": 0,
            "away": 0
        }
    ],
    "l2m": [
        {
            "PeriodName": "Q4",
            "PCTime": "01:54.4",
            "ImposibleIndicator": 0,
            "Comment": "Murray (SAC) extends his forearm into Markkanen&apos;s (UTA) front as the screen is set and the contact impedes Markkanen&apos;s FOM off-ball.",
            "CallRatingName": "CC",
            "CallType": "Foul: Personal",
            "CP": "Keegan Murray",
            "DP": "Lauri Markkanen",
            "Difficulty": "Observable",
            "VideolLink": "2167",
            "Qualifier": null,
            "posID": 1537,
            "posStart": "02:08.3",
            "posEnd": "01:54.4",
            "posTeamId": 1610612762,
            "teamIdInFavor": null,
            "errorInFavor": "",
            "imgChart": 26.530613
        },
        {
            "PeriodName": "Q4",
            "PCTime": "01:49.0",
            "ImposibleIndicator": 0,
            "Comment": "Collins (UTA) grasps and releases Lyles&apos; (SAC) arm as the two players disengage away from the ball and the contact is marginal.",
            "CallRatingName": "CNC",
            "CallType": "Foul: Personal",
            "CP": "John Collins",
            "DP": "Trey Lyles",
            "Difficulty": "Observable",
            "VideolLink": "2168",
            "Qualifier": null,
            "posID": 1538,
            "posStart": "01:54.4",
            "posEnd": "01:38.0",
            "posTeamId": 1610612758,
            "teamIdInFavor": null,
            "errorInFavor": "",
            "imgChart": 32.65306
        },
        {
            "PeriodName": "Q4",
            "PCTime": "01:41.6",
            "ImposibleIndicator": 0,
            "Comment": "Fox&apos;s (SAC) right arm comes out slightly toward Clarkson (UTA), causing marginal contact to occur when he gathers at the end of his drive.",
            "CallRatingName": "CNC",
            "CallType": "Foul: Offensive",
            "CP": "De'Aaron Fox",
            "DP": "Jordan Clarkson",
            "Difficulty": "Observable",
            "VideolLink": "2169",
            "Qualifier": null,
            "posID": 1538,
            "posStart": "01:54.4",
            "posEnd": "01:38.0",
            "posTeamId": 1610612758,
            "teamIdInFavor": null,
            "errorInFavor": "",
            "imgChart": 32.65306
        },
        {
            "PeriodName": "Q4",
            "PCTime": "01:23.0",
            "ImposibleIndicator": 0,
            "Comment": "As Markkanen (UTA) comes around the screen, McLaughlin (SAC) moves towards his space and lower leg contact occurs, which trips Markkanen and causes him to stumble towards the sideline.",
            "CallRatingName": "INC",
            "CallType": "Foul: Personal",
            "CP": "Jordan McLaughlin",
            "DP": "Lauri Markkanen",
            "Difficulty": "Observable",
            "VideolLink": "2170",
            "Qualifier": null,
            "posID": 1539,
            "posStart": "01:38.0",
            "posEnd": "01:15.7",
            "posTeamId": 1610612762,
            "teamIdInFavor": null,
            "errorInFavor": "",
            "imgChart": 44.89796
        },
        {
            "PeriodName": "Q4",
            "PCTime": "01:16.0",
            "ImposibleIndicator": 0,
            "Comment": "Fox (SAC) lowers his hand down towards the ball and incidental hand on ball contact occurs with Sexton (UTA), which deflects the loose ball away from the offensive player.",
            "CallRatingName": "CNC",
            "CallType": "Foul: Loose Ball",
            "CP": "De'Aaron Fox",
            "DP": "Collin Sexton",
            "Difficulty": "Observable",
            "VideolLink": "2171",
            "Qualifier": null,
            "posID": 1539,
            "posStart": "01:38.0",
            "posEnd": "01:15.7",
            "posTeamId": 1610612762,
            "teamIdInFavor": null,
            "errorInFavor": "",
            "imgChart": 44.89796
        },
        {
            "PeriodName": "Q4",
            "PCTime": "00:52.9",
            "ImposibleIndicator": 0,
            "Comment": "Sexton (UTA) momentarily grasps and releases Fox&apos;s (SAC) jersey shorts as he drives around the pick and the contact is marginal.",
            "CallRatingName": "CNC",
            "CallType": "Foul: Offensive",
            "CP": "Collin Sexton",
            "DP": "De'Aaron Fox",
            "Difficulty": "Observable",
            "VideolLink": "2172",
            "Qualifier": null,
            "posID": 1541,
            "posStart": "01:04.6",
            "posEnd": "00:49.1",
            "posTeamId": 1610612762,
            "teamIdInFavor": null,
            "errorInFavor": "",
            "imgChart": 30.612246
        },
        {
            "PeriodName": "Q4",
            "PCTime": "00:50.3",
            "ImposibleIndicator": 0,
            "Comment": "Fox (SAC) reaches around Sexton (UTA) and makes direct contact with his left arm, which causes Sexton to lose control of his dribble during his drive around the pick.",
            "CallRatingName": "INC",
            "CallType": "Foul: Personal",
            "CP": "De'Aaron Fox",
            "DP": "Collin Sexton",
            "Difficulty": "Observable",
            "VideolLink": "2173",
            "Qualifier": null,
            "posID": 1541,
            "posStart": "01:04.6",
            "posEnd": "00:49.1",
            "posTeamId": 1610612762,
            "teamIdInFavor": null,
            "errorInFavor": "",
            "imgChart": 30.612246
        },
        {
            "PeriodName": "Q4",
            "PCTime": "00:49.1",
            "ImposibleIndicator": 0,
            "Comment": "Murray (SAC) goes to the ground in pursuit of the loose ball and marginal lower body contact occurs with Markkanen (UTA), who is also in pursuit of the loose ball.",
            "CallRatingName": "CNC",
            "CallType": "Foul: Loose Ball",
            "CP": "Keegan Murray",
            "DP": "Lauri Markkanen",
            "Difficulty": "Observable",
            "VideolLink": "2174",
            "Qualifier": null,
            "posID": 1541,
            "posStart": "01:04.6",
            "posEnd": "00:49.1",
            "posTeamId": 1610612762,
            "teamIdInFavor": null,
            "errorInFavor": "",
            "imgChart": 30.612246
        },
        {
            "PeriodName": "Q4",
            "PCTime": "00:38.7",
            "ImposibleIndicator": 0,
            "Comment": "Replay review of the out of bounds ruled initially as a jump ball pursuant to a coach&apos;s challenge was deemed successful. Just prior to the ball going out of bounds and deemed proximate to the play, Sexton (UTA) reaches in for the ball and makes illegal contact with Fox&apos;s (SAC) left wrist after his gather, which affects his control of the ball during the driving shot attempt. The illegal arm contact precedes any potential contact by Sexton to the ball and can be deemed causal to the ball coming loose and bouncing out of bounds. Thus, Fox is awarded two free throws upon the resumption of play.",
            "CallRatingName": "CC",
            "CallType": "Foul: Shooting",
            "CP": "Collin Sexton",
            "DP": "De'Aaron Fox",
            "Difficulty": "Observable",
            "VideolLink": "2175",
            "Qualifier": null,
            "posID": 1542,
            "posStart": "00:49.1",
            "posEnd": "00:25.1",
            "posTeamId": 1610612758,
            "teamIdInFavor": null,
            "errorInFavor": "",
            "imgChart": 48.97959
        },
        {
            "PeriodName": "Q4",
            "PCTime": "00:38.5",
            "ImposibleIndicator": 0,
            "Comment": "Murray (SAC) raises his arm towards the ball and marginal brush contact occurs with Markkanen&apos;s (UTA) shoulder as he attempts to corral the rebound.",
            "CallRatingName": "CNC",
            "CallType": "Foul: Loose Ball",
            "CP": "Keegan Murray",
            "DP": "Lauri Markkanen",
            "Difficulty": "Observable",
            "VideolLink": "2176",
            "Qualifier": null,
            "posID": 1542,
            "posStart": "00:49.1",
            "posEnd": "00:25.1",
            "posTeamId": 1610612758,
            "teamIdInFavor": null,
            "errorInFavor": "",
            "imgChart": 48.97959
        },
        {
            "PeriodName": "Q4",
            "PCTime": "00:36.1",
            "ImposibleIndicator": 0,
            "Comment": "Replay review of the out of bounds called on McLaughlin (SAC)  pursuant to a coach&apos;s challenge was deemed successful. Markkanen (UTA) makes last contact with the ball prior to it rolling out of bounds. Possession is correctly awarded to Sacramento.",
            "CallRatingName": "CC",
            "CallType": "Stoppage: Out-of-Bounds",
            "CP": "Lauri Markkanen",
            "DP": "Jordan McLaughlin",
            "Difficulty": "Observable",
            "VideolLink": "2177",
            "Qualifier": null,
            "posID": 1542,
            "posStart": "00:49.1",
            "posEnd": "00:25.1",
            "posTeamId": 1610612758,
            "teamIdInFavor": null,
            "errorInFavor": "",
            "imgChart": 48.97959
        },
        {
            "PeriodName": "Q4",
            "PCTime": "00:35.5",
            "ImposibleIndicator": 0,
            "Comment": "George (UTA) makes last contact with the ball prior to it falling out of bounds. Possession is correctly awarded to Sacramento.",
            "CallRatingName": "CC",
            "CallType": "Stoppage: Out-of-Bounds",
            "CP": "Keyonte George",
            "DP": "Trey Lyles",
            "Difficulty": "Observable",
            "VideolLink": "2178",
            "Qualifier": null,
            "posID": 1542,
            "posStart": "00:49.1",
            "posEnd": "00:25.1",
            "posTeamId": 1610612758,
            "teamIdInFavor": null,
            "errorInFavor": "",
            "imgChart": 48.97959
        },
        {
            "PeriodName": "Q4",
            "PCTime": "00:29.4",
            "ImposibleIndicator": 0,
            "Comment": "Lyles (SAC) and George (UTA) both come together and collide on the perimeter, causing marginal contact to occur.",
            "CallRatingName": "CNC",
            "CallType": "Foul: Offensive",
            "CP": "Trey Lyles",
            "DP": "Keyonte George",
            "Difficulty": "Observable",
            "VideolLink": "2179",
            "Qualifier": null,
            "posID": 1542,
            "posStart": "00:49.1",
            "posEnd": "00:25.1",
            "posTeamId": 1610612758,
            "teamIdInFavor": null,
            "errorInFavor": "",
            "imgChart": 48.97959
        },
        {
            "PeriodName": "Q4",
            "PCTime": "00:27.0",
            "ImposibleIndicator": 0,
            "Comment": "Fox (SAC) releases his jump shot attempt and does not overtly extend his legs out after the release when incidental lower body contact occurs with Sexton (UTA) as both players return to the ground.",
            "CallRatingName": "CNC",
            "CallType": "Foul: Offensive",
            "CP": "De'Aaron Fox",
            "DP": "Collin Sexton",
            "Difficulty": "Observable",
            "VideolLink": "2180",
            "Qualifier": null,
            "posID": 1542,
            "posStart": "00:49.1",
            "posEnd": "00:25.1",
            "posTeamId": 1610612758,
            "teamIdInFavor": null,
            "errorInFavor": "",
            "imgChart": 48.97959
        },
        {
            "PeriodName": "Q4",
            "PCTime": "00:21.8",
            "ImposibleIndicator": 0,
            "Comment": "Sexton (UTA) receives the pass and loses control of the ball as he falls to the floor on his own accord. Utah calls a timeout prior to Sexton beginning his dribble on the ground and rising off of the floor.",
            "CallRatingName": "CNC",
            "CallType": "Turnover: Traveling",
            "CP": "Collin Sexton",
            "DP": "Kings",
            "Difficulty": "Observable",
            "VideolLink": "2181",
            "Qualifier": null,
            "posID": 1543,
            "posStart": "00:25.1",
            "posEnd": "00:16.3",
            "posTeamId": 1610612762,
            "teamIdInFavor": null,
            "errorInFavor": "",
            "imgChart": 16.32653
        },
        {
            "PeriodName": "Q4",
            "PCTime": "00:17.9",
            "ImposibleIndicator": 0,
            "Comment": "Lyles (SAC) jumps alongside Collins&apos; (UTA) path and lowers his arm down towards the ball when marginal contact occurs with Collins&apos; left arm after he takes it off of the ball during the driving shot attempt.",
            "CallRatingName": "CNC",
            "CallType": "Foul: Shooting",
            "CP": "Trey Lyles",
            "DP": "John Collins",
            "Difficulty": "Observable",
            "VideolLink": "2182",
            "Qualifier": null,
            "posID": 1543,
            "posStart": "00:25.1",
            "posEnd": "00:16.3",
            "posTeamId": 1610612762,
            "teamIdInFavor": null,
            "errorInFavor": "",
            "imgChart": 16.32653
        },
        {
            "PeriodName": "Q4",
            "PCTime": "00:17.1",
            "ImposibleIndicator": 0,
            "Comment": "Huerter (SAC) places his hand on Sexton&apos;s (UTA) back and marginal contact occurs as Sexton jumps away from the defender during the rebounding opportunity.",
            "CallRatingName": "CNC",
            "CallType": "Foul: Loose Ball",
            "CP": "Kevin Huerter",
            "DP": "Collin Sexton",
            "Difficulty": "Observable",
            "VideolLink": "2183",
            "Qualifier": null,
            "posID": 1543,
            "posStart": "00:25.1",
            "posEnd": "00:16.3",
            "posTeamId": 1610612762,
            "teamIdInFavor": null,
            "errorInFavor": "",
            "imgChart": 16.32653
        },
        {
            "PeriodName": "Q4",
            "PCTime": "00:13.0",
            "ImposibleIndicator": 0,
            "Comment": "George (UTA) commits a take foul on Fox (SAC).The transition take foul rule does not apply to the last two minutes of either the fourth quarter or overtime.",
            "CallRatingName": "CC",
            "CallType": "Foul: Personal",
            "CP": "Keyonte George",
            "DP": "De'Aaron Fox",
            "Difficulty": "Observable",
            "VideolLink": "2184",
            "Qualifier": null,
            "posID": 1544,
            "posStart": "00:16.3",
            "posEnd": "00:13.0",
            "posTeamId": 1610612758,
            "teamIdInFavor": null,
            "errorInFavor": "",
            "imgChart": 6.122449
        },
        {
            "PeriodName": "Q4",
            "PCTime": "00:08.8",
            "ImposibleIndicator": 0,
            "Comment": "Fox (SAC) moves alongside Clarkson&apos;s (UTA) path and marginal contact occurs as the two players come together during the drive.",
            "CallRatingName": "CNC",
            "CallType": "Foul: Personal",
            "CP": "De'Aaron Fox",
            "DP": "Jordan Clarkson",
            "Difficulty": "Observable",
            "VideolLink": "2185",
            "Qualifier": null,
            "posID": 1545,
            "posStart": "00:13.0",
            "posEnd": "00:03.2",
            "posTeamId": 1610612762,
            "teamIdInFavor": null,
            "errorInFavor": "",
            "imgChart": 18.367348
        },
        {
            "PeriodName": "Q4",
            "PCTime": "00:07.0",
            "ImposibleIndicator": 0,
            "Comment": "George (UTA) releases the ball within five seconds of receiving it from the game official.",
            "CallRatingName": "CNC",
            "CallType": "Turnover: 5 Second Violation",
            "CP": "Keyonte George",
            "DP": "Kings",
            "Difficulty": "Observable",
            "VideolLink": "2186",
            "Qualifier": null,
            "posID": 1545,
            "posStart": "00:13.0",
            "posEnd": "00:03.2",
            "posTeamId": 1610612762,
            "teamIdInFavor": null,
            "errorInFavor": "",
            "imgChart": 18.367348
        },
        {
            "PeriodName": "Q4",
            "PCTime": "00:06.5",
            "ImposibleIndicator": 0,
            "Comment": "Huerter (SAC) places and swiftly removes his hand from Sexton&apos;s (UTA) front at the start of his drive and the contact is marginal.",
            "CallRatingName": "CNC",
            "CallType": "Foul: Personal",
            "CP": "Kevin Huerter",
            "DP": "Collin Sexton",
            "Difficulty": "Observable",
            "VideolLink": "2187",
            "Qualifier": null,
            "posID": 1545,
            "posStart": "00:13.0",
            "posEnd": "00:03.2",
            "posTeamId": 1610612762,
            "teamIdInFavor": null,
            "errorInFavor": "",
            "imgChart": 18.367348
        },
        {
            "PeriodName": "Q4",
            "PCTime": "00:03.2",
            "ImposibleIndicator": 0,
            "Comment": "Fox (SAC) commits a take foul on Clarkson (UTA).",
            "CallRatingName": "CC",
            "CallType": "Foul: Personal",
            "CP": "De'Aaron Fox",
            "DP": "Jordan Clarkson",
            "Difficulty": "Observable",
            "VideolLink": "2190",
            "Qualifier": null,
            "posID": 1545,
            "posStart": "00:13.0",
            "posEnd": "00:03.2",
            "posTeamId": 1610612762,
            "teamIdInFavor": null,
            "errorInFavor": "",
            "imgChart": 18.367348
        },
        {
            "PeriodName": "Q4",
            "PCTime": "00:03.2",
            "ImposibleIndicator": 0,
            "Comment": "Clarkson&apos;s (UTA) free throw attempt does not come into contact with the rim. This is a violation and possession is correctly awarded to Sacramento.",
            "CallRatingName": "CC",
            "CallType": "Free Throw Technical",
            "CP": "Jordan Clarkson",
            "DP": "Kings",
            "Difficulty": "Observable",
            "VideolLink": "2189",
            "Qualifier": null,
            "posID": 1545,
            "posStart": "00:13.0",
            "posEnd": "00:03.2",
            "posTeamId": 1610612762,
            "teamIdInFavor": null,
            "errorInFavor": "",
            "imgChart": 18.367348
        },
        {
            "PeriodName": "Q4",
            "PCTime": "00:03.2",
            "ImposibleIndicator": 0,
            "Comment": "George (UTA) and McLaughlin (SAC) engage and disengage during the inbounds and the contact is marginal.",
            "CallRatingName": "CNC",
            "CallType": "Foul: Personal",
            "CP": "Keyonte George",
            "DP": "Jordan McLaughlin",
            "Difficulty": "Observable",
            "VideolLink": "2188",
            "Qualifier": null,
            "posID": 1546,
            "posStart": "00:03.2",
            "posEnd": "00:01.8",
            "posTeamId": 1610612758,
            "teamIdInFavor": null,
            "errorInFavor": "",
            "imgChart": 2.0408163
        },
        {
            "PeriodName": "Q4",
            "PCTime": "00:01.8",
            "ImposibleIndicator": 0,
            "Comment": "Sexton (UTA) commits a take foul on Fox (SAC).",
            "CallRatingName": "CC",
            "CallType": "Foul: Personal",
            "CP": "Collin Sexton",
            "DP": "De'Aaron Fox",
            "Difficulty": "Observable",
            "VideolLink": "2191",
            "Qualifier": null,
            "posID": 1546,
            "posStart": "00:03.2",
            "posEnd": "00:01.8",
            "posTeamId": 1610612758,
            "teamIdInFavor": null,
            "errorInFavor": "",
            "imgChart": 2.0408163
        }
    ]
}